README.md
setup.py
cubespa/__init__.py
cubespa/cubespa.py
cubespa/data.py
cubespa/moment_maps.py
cubespa/overlays.py
cubespa/pvds.py
cubespa/spectra.py
cubespa/utils.py
cubespa.egg-info/PKG-INFO
cubespa.egg-info/SOURCES.txt
cubespa.egg-info/dependency_links.txt
cubespa.egg-info/top_level.txt
cubespa/analysis/__init__.py
cubespa/analysis/flux_analysis.py
cubespa/modeling/__init__.py
cubespa/modeling/velocity_map.py
cubespa/plotting/__init__.py
cubespa/plotting/channel_map_plots.py
cubespa/plotting/mommap_plots.py
cubespa/plotting/overlay_plots.py
cubespa/plotting/pvd_plots.py
cubespa/plotting/spectra_plots.py
cubespa/plotting/util_plots.py
cubespa/plotting/utils.py
personal/__init__.py
tests/__init__.py
tests/util_tests.py